{
    "cmp-path": {
        "cargoLocks": null,
        "date": "2022-10-03",
        "extract": null,
        "name": "cmp-path",
        "passthru": null,
        "pinned": false,
        "src": {
            "deepClone": false,
            "fetchSubmodules": false,
            "leaveDotGit": true,
            "name": null,
            "owner": "hrsh7th",
            "repo": "cmp-path",
            "rev": "91ff86cd9c29299a64f968ebb45846c485725f23",
            "sha256": "sha256-Fm7L5IJ/Dp+lf9qsMHzFLF85oaaU5wXr/rEa5fzI6c8=",
            "type": "github"
        },
        "version": "91ff86cd9c29299a64f968ebb45846c485725f23"
    }
}