{
    "null-ls-nvim": {
        "cargoLocks": null,
        "date": "2023-08-11",
        "extract": null,
        "name": "null-ls-nvim",
        "passthru": null,
        "pinned": false,
        "src": {
            "deepClone": false,
            "fetchSubmodules": false,
            "leaveDotGit": false,
            "name": null,
            "owner": "jose-elias-alvarez",
            "repo": "null-ls.nvim",
            "rev": "0010ea927ab7c09ef0ce9bf28c2b573fc302f5a7",
            "sha256": "sha256-cWA0rzkOp/ekVKaFee7iea1lhnqKtWUIU+fW5M950wI=",
            "type": "github"
        },
        "version": "0010ea927ab7c09ef0ce9bf28c2b573fc302f5a7"
    }
}