{
    "neogit": {
        "cargoLocks": null,
        "date": "2024-02-05",
        "extract": null,
        "name": "neogit",
        "passthru": null,
        "pinned": false,
        "src": {
            "deepClone": false,
            "fetchSubmodules": false,
            "leaveDotGit": false,
            "name": null,
            "owner": "NeogitOrg",
            "repo": "neogit",
            "rev": "536b4cfc009fc6d8bd771f010f04d48204533fae",
            "sha256": "sha256-+IcIQT09Tx6ssvhBkbSqFisUsPK92ZjnJ7SFdRosuTo=",
            "type": "github"
        },
        "version": "536b4cfc009fc6d8bd771f010f04d48204533fae"
    }
}