{
    "git-worktree-nvim": {
        "cargoLocks": null,
        "date": "2024-01-04",
        "extract": null,
        "name": "git-worktree-nvim",
        "passthru": null,
        "pinned": false,
        "src": {
            "deepClone": false,
            "fetchSubmodules": false,
            "leaveDotGit": false,
            "name": null,
            "owner": "polarmutex",
            "repo": "git-worktree.nvim",
            "rev": "ee1030d6b987f381c05f7228565a63e124e93ad3",
            "sha256": "sha256-2XgPF8uzLgyDUGBiqZJZN/jWV369jqfkPGEHnyeG6KI=",
            "type": "github"
        },
        "version": "ee1030d6b987f381c05f7228565a63e124e93ad3"
    }
}